pipfont/__init__.py
pipfont-3.0.0.dist-info/METADATA
pipfont-3.0.0.dist-info/WHEEL
pipfont-3.0.0.dist-info/top_level.txt
pipfont-3.0.0.dist-info/RECORD
