Metadata-Version: 2.1
Name: pipfont
Version: 3.0.0
Summary: A Python3 package to Manage fonts and customize fonts in the terminal.
Home-page: UNKNOWN
Author: ЕntchenBuilds
Author-email: ЕntchenBuilds@gmail.com
License: UNKNOWN
Keywords: python
Platform: UNKNOWN
Classifier: Operating System :: Microsoft :: Windows
